{
  "kind": "parsed_program",
  "source_path": "igniter-lang/experiments/source_to_semanticir_fixture/negative_evidence_less_alert.ig",
  "source_hash": "sha256:b2b44c799dba43f705081edaeff37532773abca340bf22e6d55cc9b6c8cd1779",
  "grammar_version": "0.1.0",
  "module": "Fixture.SourceToSemanticIR.NegativeAlert",
  "imports": [],
  "traits": [],
  "impls": [],
  "contract_shapes": [],
  "contracts": [
    {
      "kind": "contract",
      "name": "BadEvidenceLessAlertGate",
      "type_params": [],
      "body": [
        {
          "kind": "input",
          "name": "alert",
          "type_annotation": "EvidenceLinkedAlertInput"
        },
        {
          "kind": "compute",
          "name": "signal_present",
          "expr": {
            "kind": "binary_op",
            "op": ">",
            "left": {
              "kind": "field_access",
              "object": {
                "kind": "ref",
                "name": "alert"
              },
              "field": "signal_count"
            },
            "right": {
              "kind": "literal",
              "value": 0,
              "type_tag": "Integer"
            }
          }
        },
        {
          "kind": "compute",
          "name": "claim_present",
          "expr": {
            "kind": "binary_op",
            "op": ">",
            "left": {
              "kind": "field_access",
              "object": {
                "kind": "ref",
                "name": "alert"
              },
              "field": "claim_count"
            },
            "right": {
              "kind": "literal",
              "value": 0,
              "type_tag": "Integer"
            }
          }
        },
        {
          "kind": "compute",
          "name": "allowed",
          "expr": {
            "kind": "binary_op",
            "op": "&&",
            "left": {
              "kind": "ref",
              "name": "signal_present"
            },
            "right": {
              "kind": "ref",
              "name": "claim_present"
            }
          }
        },
        {
          "kind": "output",
          "name": "allowed",
          "type_annotation": "Bool"
        }
      ]
    }
  ],
  "types": [
    {
      "kind": "type",
      "name": "EvidenceLinkedAlertInput",
      "fields": [
        {
          "name": "signal_count",
          "type_annotation": "Integer",
          "optional": false
        },
        {
          "name": "claim_count",
          "type_annotation": "Integer",
          "optional": false
        },
        {
          "name": "valid_until",
          "type_annotation": "String",
          "optional": false
        },
        {
          "name": "confidence_label",
          "type_annotation": "ConfidenceLabel",
          "optional": false
        }
      ]
    }
  ],
  "functions": [],
  "pipelines": [],
  "parse_errors": []
}
