{
  "artifact_hash": "sha256:e6cd1c5cc5ccb949f4fd72f7a46bef04db95d1b2a646a860178ed2d24166d77b",
  "compute_nodes": [
    {
      "dependencies": [
        "input:res_in"
      ],
      "expression": {
        "kind": "apply",
        "operands": [
          {
            "kind": "ref",
            "name": "res_in",
            "resolved_type": {
              "kind": "type_ref",
              "name": "Result",
              "params": [
                {
                  "kind": "type_ref",
                  "name": "Integer",
                  "params": []
                },
                {
                  "kind": "type_ref",
                  "name": "String",
                  "params": []
                }
              ]
            }
          }
        ],
        "operator": "is_ok",
        "resolved_type": {
          "name": "Bool",
          "params": []
        }
      },
      "fragment_class": "core",
      "kind": "compute",
      "lifecycle": "session",
      "name": "is_ok_val",
      "node_id": "node_is_ok_val",
      "obs_kind": "value_observation",
      "type_tag": "Bool"
    },
    {
      "dependencies": [
        "input:res_in"
      ],
      "expression": {
        "kind": "apply",
        "operands": [
          {
            "kind": "ref",
            "name": "res_in",
            "resolved_type": {
              "kind": "type_ref",
              "name": "Result",
              "params": [
                {
                  "kind": "type_ref",
                  "name": "Integer",
                  "params": []
                },
                {
                  "kind": "type_ref",
                  "name": "String",
                  "params": []
                }
              ]
            }
          }
        ],
        "operator": "is_err",
        "resolved_type": {
          "name": "Bool",
          "params": []
        }
      },
      "fragment_class": "core",
      "kind": "compute",
      "lifecycle": "session",
      "name": "is_err_val",
      "node_id": "node_is_err_val",
      "obs_kind": "value_observation",
      "type_tag": "Bool"
    },
    {
      "dependencies": [
        "input:res_in"
      ],
      "expression": {
        "kind": "apply",
        "operands": [
          {
            "kind": "ref",
            "name": "res_in",
            "resolved_type": {
              "kind": "type_ref",
              "name": "Result",
              "params": [
                {
                  "kind": "type_ref",
                  "name": "Integer",
                  "params": []
                },
                {
                  "kind": "type_ref",
                  "name": "String",
                  "params": []
                }
              ]
            }
          },
          {
            "body": {
              "kind": "apply",
              "operands": [
                {
                  "kind": "ref",
                  "name": "x",
                  "resolved_type": {
                    "name": "Integer",
                    "params": []
                  }
                },
                {
                  "kind": "literal",
                  "literal_type": "int",
                  "resolved_type": {
                    "name": "Integer",
                    "params": []
                  },
                  "type_tag": "Integer",
                  "value": 5
                }
              ],
              "operator": "stdlib.integer.mul",
              "resolved_type": {
                "name": "Integer",
                "params": []
              }
            },
            "kind": "lambda",
            "params": [
              "x"
            ],
            "resolved_type": {
              "name": "Unknown",
              "params": []
            }
          }
        ],
        "operator": "map",
        "resolved_type": {
          "name": "Result",
          "params": [
            {
              "name": "Integer",
              "params": []
            },
            {
              "kind": "type_ref",
              "name": "String",
              "params": []
            }
          ]
        }
      },
      "fragment_class": "core",
      "kind": "compute",
      "lifecycle": "session",
      "name": "mapped",
      "node_id": "node_mapped",
      "obs_kind": "value_observation",
      "type_tag": "Result[Integer,String]"
    },
    {
      "dependencies": [
        "input:res_in"
      ],
      "expression": {
        "kind": "apply",
        "operands": [
          {
            "kind": "ref",
            "name": "res_in",
            "resolved_type": {
              "kind": "type_ref",
              "name": "Result",
              "params": [
                {
                  "kind": "type_ref",
                  "name": "Integer",
                  "params": []
                },
                {
                  "kind": "type_ref",
                  "name": "String",
                  "params": []
                }
              ]
            }
          },
          {
            "body": {
              "kind": "apply",
              "operands": [
                {
                  "kind": "apply",
                  "operands": [
                    {
                      "kind": "ref",
                      "name": "x",
                      "resolved_type": {
                        "name": "Integer",
                        "params": []
                      }
                    },
                    {
                      "kind": "literal",
                      "literal_type": "int",
                      "resolved_type": {
                        "name": "Integer",
                        "params": []
                      },
                      "type_tag": "Integer",
                      "value": 100
                    }
                  ],
                  "operator": "stdlib.integer.add",
                  "resolved_type": {
                    "name": "Integer",
                    "params": []
                  }
                }
              ],
              "operator": "ok",
              "resolved_type": {
                "name": "Result",
                "params": [
                  {
                    "name": "Integer",
                    "params": []
                  },
                  {
                    "name": "Unknown",
                    "params": []
                  }
                ]
              }
            },
            "kind": "lambda",
            "params": [
              "x"
            ],
            "resolved_type": {
              "name": "Unknown",
              "params": []
            }
          }
        ],
        "operator": "and_then",
        "resolved_type": {
          "name": "Result",
          "params": [
            {
              "name": "Integer",
              "params": []
            },
            {
              "name": "Unknown",
              "params": []
            }
          ]
        }
      },
      "fragment_class": "core",
      "kind": "compute",
      "lifecycle": "session",
      "name": "flat_mapped",
      "node_id": "node_flat_mapped",
      "obs_kind": "value_observation",
      "type_tag": "Result[Integer,Unknown]"
    },
    {
      "dependencies": [
        "input:res_in",
        "input:fallback"
      ],
      "expression": {
        "kind": "apply",
        "operands": [
          {
            "kind": "ref",
            "name": "res_in",
            "resolved_type": {
              "kind": "type_ref",
              "name": "Result",
              "params": [
                {
                  "kind": "type_ref",
                  "name": "Integer",
                  "params": []
                },
                {
                  "kind": "type_ref",
                  "name": "String",
                  "params": []
                }
              ]
            }
          },
          {
            "kind": "ref",
            "name": "fallback",
            "resolved_type": {
              "name": "Integer",
              "params": []
            }
          }
        ],
        "operator": "unwrap_or",
        "resolved_type": {
          "name": "Integer",
          "params": []
        }
      },
      "fragment_class": "core",
      "kind": "compute",
      "lifecycle": "session",
      "name": "unwrapped_or_val",
      "node_id": "node_unwrapped_or_val",
      "obs_kind": "value_observation",
      "type_tag": "Integer"
    }
  ],
  "contract_id": "ResultWorkflow",
  "escape_set": [],
  "fragment_class": "core",
  "input_ports": [
    {
      "lifecycle": "local",
      "name": "res_in",
      "required": true,
      "type_tag": "Result[Integer,String]"
    },
    {
      "lifecycle": "local",
      "name": "fallback",
      "required": true,
      "type_tag": "Integer"
    }
  ],
  "lifecycle": "session",
  "name": "ResultWorkflow",
  "output_ports": [
    {
      "lifecycle": "session",
      "name": "is_ok_val",
      "required": true,
      "type_tag": "Bool"
    },
    {
      "lifecycle": "session",
      "name": "is_err_val",
      "required": true,
      "type_tag": "Bool"
    },
    {
      "lifecycle": "session",
      "name": "mapped",
      "required": true,
      "type_tag": "Result[Integer,String]"
    },
    {
      "lifecycle": "session",
      "name": "flat_mapped",
      "required": true,
      "type_tag": "Result[Integer,String]"
    },
    {
      "lifecycle": "session",
      "name": "unwrapped_or_val",
      "required": true,
      "type_tag": "Integer"
    }
  ],
  "source_contract_ref": "contract/ResultWorkflow/sha256:745475200ea9380e6d73f8d4",
  "type_signature": {
    "inputs": {
      "fallback": "Integer",
      "res_in": "Result[Integer,String]"
    },
    "outputs": {
      "flat_mapped": "Result[Integer,String]",
      "is_err_val": "Bool",
      "is_ok_val": "Bool",
      "mapped": "Result[Integer,String]",
      "unwrapped_or_val": "Integer"
    }
  }
}
